campbel/__init__.py
campbel/AWS/__init__.py
campbel/AWS/Rds/Rds.py
campbel/AWS/Rds/__init__.py
campbel/AWS/S3/S3.py
campbel/AWS/S3/__init__.py
campbel/AWS/S3/test.py
campbel-0.0.42.dist-info/DESCRIPTION.rst
campbel-0.0.42.dist-info/METADATA
campbel-0.0.42.dist-info/RECORD
campbel-0.0.42.dist-info/WHEEL
campbel-0.0.42.dist-info/entry_points.txt
campbel-0.0.42.dist-info/metadata.json
campbel-0.0.42.dist-info/top_level.txt
