Metadata-Version: 2.0
Name: campbel
Version: 0.0.42
Summary: Convenient tool"),
Home-page: https://github.com/campbel2525/campbel
Author: Ryuichi Furuya
Author-email: campbel2525@gmail.com
License: MIT
Platform: UNKNOWN
Classifier: Programming Language :: Python :: 2.7
Classifier: Programming Language :: Python :: 3.6
Requires-Dist: boto
Requires-Dist: pymysql
